securebot_sdk/__init__.py
securebot_sdk/core/__init__.py
securebot_sdk/core/config.py
securebot_sdk/core/decorators.py
securebot_sdk/core/http_client.py
securebot_sdk/core/identity_manager.py
securebot_sdk/core/identity_provider.py
securebot_sdk/core/permission_handler.py
securebot_sdk/identity/__init__.py
securebot_sdk/identity/crewai/__init__.py
securebot_sdk/identity/crewai/permission_handler.py
securebot_sdk/logger/__init__.py
securebot_sdk/logger/log.py
securebot_sdk/tracing/__init__.py
securebot_sdk/tracing/tracing.py
securebot_sdk-0.1.1.dist-info/METADATA
securebot_sdk-0.1.1.dist-info/WHEEL
securebot_sdk-0.1.1.dist-info/licenses/LICENSE
securebot_sdk-0.1.1.dist-info/RECORD
